README.md
setup.py
pixelpainter/__init__.py
pixelpainter/core.py
pixelpainter/libs.py
pixelpainter.egg-info/PKG-INFO
pixelpainter.egg-info/SOURCES.txt
pixelpainter.egg-info/dependency_links.txt
pixelpainter.egg-info/entry_points.txt
pixelpainter.egg-info/requires.txt
pixelpainter.egg-info/top_level.txt