Metadata-Version: 2.1
Name: pixelpainter
Version: 0.1
Summary: Convert images to HTML.
Home-page: https://github.com/Jalkhov/pixelpainter
Author: Pedro Torcatt
Author-email: pedrotorcattsoto@gmail.com
License: MIT
Keywords: paint html pixel convert image
Platform: UNKNOWN
Classifier: Topic :: Utilities
Classifier: Environment :: Console
Classifier: Programming Language :: Python :: 3
Classifier: License :: OSI Approved :: MIT License
Classifier: Operating System :: Microsoft :: Windows
Classifier: Development Status :: 5 - Production/Stable
Classifier: Topic :: Scientific/Engineering :: Image Processing
